jocasta/__init__.py
jocasta/collector.py
jocasta/validators.py
jocasta/command_line/__init__.py
jocasta/command_line/setup.py
jocasta/connectors/__init__.py
jocasta/connectors/constants.py
jocasta/connectors/csv_file.py
jocasta/connectors/dweet.py
jocasta/connectors/file_system.py
jocasta/connectors/influx.py
jocasta/connectors/io_adafruit.py
jocasta/inputs/__init__.py
jocasta/inputs/serial_connector.py
jocasta-0.3.2.dist-info/LICENSE
jocasta-0.3.2.dist-info/METADATA
jocasta-0.3.2.dist-info/WHEEL
jocasta-0.3.2.dist-info/entry_points.txt
jocasta-0.3.2.dist-info/top_level.txt
jocasta-0.3.2.dist-info/RECORD
