Metadata-Version: 2.1
Name: jocasta
Version: 0.3.2
Summary: Fetch sensor data.
Home-page: https://github.com/chrishannam/jocasta
Author: Chris Hannam
Author-email: ch@chrishannam.co.uk
License: UNKNOWN
Platform: UNKNOWN
Classifier: Programming Language :: Python :: 3
Classifier: License :: OSI Approved :: Apache Software License
Classifier: Operating System :: OS Independent
Requires-Dist: adafruit-io (~=2.4.0)
Requires-Dist: click (~=7.1.2)
Requires-Dist: dweepy (~=0.3.0)
Requires-Dist: influxdb (~=5.3.0)
Requires-Dist: pyserial (~=3.4)
Requires-Dist: psutil (~=5.7.0)
Requires-Dist: redis (~=2.10.6)
Requires-Dist: tabulate (~=0.8.7)
